ecospat/.DS_Store
ecospat/__init__.py
ecospat/common.py
ecospat/ecospat.py
ecospat/foliummap.py
ecospat/mapping.py
ecospat/name_references.py
ecospat/references_data.py
ecospat/stand_alone_functions.py
ecospat-1.1.0.dist-info/licenses/LICENSE
ecospat-1.1.0.dist-info/METADATA
ecospat-1.1.0.dist-info/WHEEL
ecospat-1.1.0.dist-info/entry_points.txt
ecospat-1.1.0.dist-info/top_level.txt
ecospat-1.1.0.dist-info/RECORD
