Metadata-Version: 2.4
Name: ecospat
Version: 1.1.0
Summary: A python package that uses GBIF data to categorize the range edges of species through time to understand patterns of range movement, population dynamics, and individual persistence.
Author-email: Alivia Nytko <anytko@vols.utk.edu>
License: MIT License
Project-URL: Homepage, https://github.com/anytko/ecospat
Keywords: ecospat
Classifier: Intended Audience :: Developers
Classifier: License :: OSI Approved :: MIT License
Classifier: Natural Language :: English
Classifier: Programming Language :: Python :: 3.8
Classifier: Programming Language :: Python :: 3.9
Classifier: Programming Language :: Python :: 3.10
Classifier: Programming Language :: Python :: 3.11
Classifier: Programming Language :: Python :: 3.12
Requires-Python: >=3.8
License-File: LICENSE
Requires-Dist: fiona
Requires-Dist: folium
Requires-Dist: geopandas
Requires-Dist: geopy
Requires-Dist: ipyleaflet
Requires-Dist: IPython
Requires-Dist: ipywidgets
Requires-Dist: leafmap
Requires-Dist: localtileserver
Requires-Dist: mapclassify
Requires-Dist: matplotlib
Requires-Dist: numpy
Requires-Dist: pandas
Requires-Dist: pydeck
Requires-Dist: pygbif
Requires-Dist: pytest
Requires-Dist: rasterio
Requires-Dist: rasterstats
Requires-Dist: requests
Requires-Dist: scikit-learn
Requires-Dist: scipy
Requires-Dist: setuptools
Requires-Dist: shapely
Provides-Extra: all
Requires-Dist: ecospat[extra]; extra == "all"
Provides-Extra: extra
Requires-Dist: pandas; extra == "extra"
Dynamic: license-file
